pycdep
