Metadata-Version: 1.0
Name: pycdep
Version: 0.0.2
Summary: Header file dependency analysis and visualization for C/C++.
Home-page: http://pycdep.sourceforge.net
Author: stefaan himpe
Author-email: stefaan.himpe@gmail.com
License: GPLv3
Keywords: header file dependency analysis visualization C C++ prolog
Platform: UNKNOWN
Classifier: Development Status :: 3 - Alpha
Classifier: Environment :: Console
Classifier: Intended Audience :: Developers
Classifier: License :: OSI Approved :: GNU General Public License (GPL)
Classifier: Natural Language :: English
Classifier: Operating System :: OS Independent
Classifier: Programming Language :: Python :: 2.6
Classifier: Programming Language :: Prolog
Classifier: Topic :: Software Development :: Quality Assurance
